[
  {
    "username": "frontendmonitor",
    "password": "password",
    "lastlogindate": "2023-04-27T16:58:05.153Z",
    "numberloginattempts": 34,
    "userachievement": {
      "score": 1000
    }
  },
  {
    "username": "user1",
    "password": "123",
    "lastlogindate": "2023-04-27T16:58:05.158Z",
    "numberloginattempts": 256,
    "userachievement": {
      "score": 1000
    }
  },
  {
    "username": "user2",
    "password": "123",
    "lastlogindate": "2023-04-27T16:58:05.158Z",
    "numberloginattempts": 256,
    "userachievement": {
      "score": 1000
    }
  },
  {
    "username": "user3",
    "password": "123",
    "lastlogindate": "2023-04-27T16:58:05.158Z",
    "numberloginattempts": 256,
    "userachievement": {
      "score": 1000
    }
  }
]